spikes/__init__.py
spikes/__version__.py
spikes/base.py
spikes/encoder.py
spikes/utility.py
spikes/utils/__init__.py
spikes/utils/errors.py
spikes/utils/read_data.py
spikes/utils/utils.py
pyspikes-0.2.9.dist-info/LICENSE
pyspikes-0.2.9.dist-info/METADATA
pyspikes-0.2.9.dist-info/WHEEL
pyspikes-0.2.9.dist-info/top_level.txt
pyspikes-0.2.9.dist-info/RECORD
