Metadata-Version: 2.1
Name: pyspikes
Version: 0.2.9
Summary: Spiking Neural Network Spike Encoders
Home-page: https://github.com/akshaybabloo/Spikes
Author: Akshay Raj Gollahalli
Author-email: akshay@gollahalli.com
License: BSD-3-Clause
Keywords: Spiking Neural Network spike encoder
Platform: UNKNOWN
Classifier: Development Status :: 4 - Beta
Classifier: Intended Audience :: Science/Research
Classifier: Natural Language :: English
Classifier: Operating System :: OS Independent
Classifier: License :: OSI Approved :: MIT License
Classifier: Programming Language :: Python :: 3
Classifier: Programming Language :: Python :: 3.5
Classifier: Programming Language :: Python :: 3.6
Classifier: Programming Language :: Python :: 3.7
Classifier: Topic :: Scientific/Engineering
Requires-Dist: scikit-learn (>=0.17.0)
Requires-Dist: numpy (>=1.10.3)
Requires-Dist: scipy (>=0.17.1)
